universal_api_connector/__init__.py
universal_api_connector/connector.py
universal_api_connector/exceptions.py
universal_api_connector/utils/__init__.py
universal_api_connector/utils/logger.py
universal_api_connector/utils/validators.py
universal_api_connector_v2-0.0.4.dist-info/licenses/LICENSE
universal_api_connector_v2-0.0.4.dist-info/METADATA
universal_api_connector_v2-0.0.4.dist-info/WHEEL
universal_api_connector_v2-0.0.4.dist-info/top_level.txt
universal_api_connector_v2-0.0.4.dist-info/RECORD
